{
    "student_id": "송태민",
    "name": "순두부",
    "image": "images/soft tofu.png",
    "image_prompt": "콩 4~5되를 곱게 가루 내어 물과 섞어 초사(篩, 생명주실로 엮은 고운 체)에 찌꺼기를 걸러 낸다. 콩물이 끓어오르면 그치고 간수를 넣어 엉기도록 기다린다. 기름진 고기, 생강, 산초, 청장을 같이 넣어 탕을 만들어 내면 더욱 좋다. 보자기에 싸면 연두부(軟豆泡)가 되는데 양은 마음대로 한다.",
    "ingredients": [
        "콩 4~5되 주재료",
        "간수 주료",
        "기름진 고기",
        "생강 부재료",
        "산초 부재료",
        "청장 부재료"
    ],
    "original": "太四五升，細末和水，用篩去滓。沸湯出歇，入艮水待凝。膏肉姜椒醬和作湯供之，甚佳。則軟豆泡，多少任意。",
    "translated": "콩 4~5되를 곱게 가루 내어 물과 섞어 초사(篩, 생명주실로 엮은 고운 체)에 찌꺼기를 걸러 낸다. 콩물이 끓어오르면 그치고 간수를 넣어 엉기도록 기다린다. 기름진 고기, 생강, 산초, 청장을 같이 넣어 탕을 만들어 내면 더욱 좋다. 보자기에 싸면 연두부(軟豆泡)가 되는데 양은 마음대로 한다.",
    "source": "산가요록(山家要錄",
    "comment": "이 음식에 대한 자신의 생각, 또는 다른 사람이 알아줬으면 하는 내용을 적습니다."
}
